pypom/__init__.py
pypom/driver.py
pypom/exception.py
pypom/hooks.py
pypom/page.py
pypom/region.py
pypom/selenium_driver.py
pypom/splinter_driver.py
pypom/view.py
pypom/interfaces/__init__.py
pypom/interfaces/driver.py
PyPOM-2.2.4.dist-info/LICENSE.txt
PyPOM-2.2.4.dist-info/METADATA
PyPOM-2.2.4.dist-info/WHEEL
PyPOM-2.2.4.dist-info/top_level.txt
PyPOM-2.2.4.dist-info/RECORD
