Metadata-Version: 2.1
Name: PyPOM
Version: 2.2.4
Summary: python page object model for selenium
Home-page: https://github.com/KeshavaReddy1101/PyPOM
Author: Keshava Reddy Kankanala
Author-email: keshav.kankanala@gmail.com
License: Mozilla Public License 2.0 (MPL 2.0)
Keywords: pypom page object model selenium
Classifier: Development Status :: 5 - Production/Stable
Classifier: Intended Audience :: Developers
Classifier: License :: OSI Approved :: Mozilla Public License 2.0 (MPL 2.0)
Classifier: Operating System :: POSIX
Classifier: Operating System :: Microsoft :: Windows
Classifier: Operating System :: MacOS :: MacOS X
Classifier: Topic :: Software Development :: Quality Assurance
Classifier: Topic :: Software Development :: Testing
Classifier: Topic :: Utilities
Classifier: Programming Language :: Python
Classifier: Programming Language :: Python :: 2.7
Classifier: Programming Language :: Python :: 3.6
License-File: LICENSE.txt
Requires-Dist: zope.interface
Requires-Dist: zope.component
Requires-Dist: pluggy
Requires-Dist: selenium
Provides-Extra: splinter
Requires-Dist: splinter ; extra == 'splinter'
